{
  "fileExplorerIconPosition": "file-name-left",
  "statusColors": {
    "active": "var(--text-success)",
    "onHold": "var(--text-warning)",
    "completed": "var(--text-accent)",
    "dropped": "var(--text-error)",
    "unknown": "var(--text-muted)",
    "inProgress": "#2196F3",
    "true": "#ffffff",
    "false": "#ffffff"
  },
  "showStatusBar": true,
  "autoHideStatusBar": false,
  "customStatuses": [],
  "showStatusIconsInExplorer": true,
  "hideUnknownStatusInExplorer": true,
  "enabledTemplates": [
    "colorful"
  ],
  "useCustomStatusesOnly": false,
  "useMultipleStatuses": false,
  "tagPrefix": "notestatus",
  "strictStatuses": true,
  "quickStatusCommands": [
    "active",
    "completed",
    "false",
    "true",
    "colorful:idea",
    "colorful:completed",
    "colorful:inProgress"
  ],
  "unknownStatusIcon": "",
  "unknownStatusColor": "#8b949e",
  "statusBarNoStatusText": "No status",
  "statusBarShowNoStatusIcon": false,
  "statusBarShowNoStatusText": false,
  "vaultSizeLimit": 15000,
  "collapsedStatuses": {},
  "compactView": false,
  "excludeUnknownStatus": true
}